stock_modelscope_mcp_server/__init__.py
stock_modelscope_mcp_server/server.py
stock_modelscope_mcp_server-0.1.0.dist-info/METADATA
stock_modelscope_mcp_server-0.1.0.dist-info/WHEEL
stock_modelscope_mcp_server-0.1.0.dist-info/entry_points.txt
stock_modelscope_mcp_server-0.1.0.dist-info/RECORD
