Metadata-Version: 2.4
Name: stock-modelscope-mcp-server
Version: 0.1.0
Summary: Add your description here
Author-email: master <2194786607@qq.com>
Requires-Python: >=3.12
Requires-Dist: akshare>=1.17.20
Requires-Dist: mcp[cli]>=1.6.0
